nvidia_physicsnemo-1.3.0.dist-info/licenses/LICENSE.txt
physicsnemo/__init__.py
physicsnemo/constants.py
physicsnemo/active_learning/__init__.py
physicsnemo/active_learning/_registry.py
physicsnemo/active_learning/config.py
physicsnemo/active_learning/driver.py
physicsnemo/active_learning/logger.py
physicsnemo/active_learning/loop.py
physicsnemo/active_learning/protocols.py
physicsnemo/datapipes/__init__.py
physicsnemo/datapipes/datapipe.py
physicsnemo/datapipes/meta.py
physicsnemo/datapipes/benchmarks/__init__.py
physicsnemo/datapipes/benchmarks/darcy.py
physicsnemo/datapipes/benchmarks/kelvin_helmholtz.py
physicsnemo/datapipes/benchmarks/kernels/__init__.py
physicsnemo/datapipes/benchmarks/kernels/finite_difference.py
physicsnemo/datapipes/benchmarks/kernels/finite_volume.py
physicsnemo/datapipes/benchmarks/kernels/indexing.py
physicsnemo/datapipes/benchmarks/kernels/initialization.py
physicsnemo/datapipes/benchmarks/kernels/utils.py
physicsnemo/datapipes/cae/__init__.py
physicsnemo/datapipes/cae/cae_dataset.py
physicsnemo/datapipes/cae/domino_datapipe.py
physicsnemo/datapipes/cae/mesh_datapipe.py
physicsnemo/datapipes/cae/readers.py
physicsnemo/datapipes/climate/__init__.py
physicsnemo/datapipes/climate/climate.py
physicsnemo/datapipes/climate/era5_hdf5.py
physicsnemo/datapipes/climate/era5_netcdf.py
physicsnemo/datapipes/climate/synthetic.py
physicsnemo/datapipes/climate/utils/__init__.py
physicsnemo/datapipes/climate/utils/invariant.py
physicsnemo/datapipes/climate/utils/zenith_angle.py
physicsnemo/datapipes/gnn/__init__.py
physicsnemo/datapipes/gnn/ahmed_body_dataset.py
physicsnemo/datapipes/gnn/ahmed_body_dataset_dgl.py
physicsnemo/datapipes/gnn/bsms.py
physicsnemo/datapipes/gnn/drivaernet_dataset.py
physicsnemo/datapipes/gnn/drivaernet_dataset_dgl.py
physicsnemo/datapipes/gnn/hydrographnet_dataset.py
physicsnemo/datapipes/gnn/hydrographnet_dataset_dgl.py
physicsnemo/datapipes/gnn/lagrangian_dataset.py
physicsnemo/datapipes/gnn/lagrangian_dataset_dgl.py
physicsnemo/datapipes/gnn/lagrangian_reading_utils.py
nvidia_physicsnemo-1.3.0.dist-info/METADATA
nvidia_physicsnemo-1.3.0.dist-info/WHEEL
nvidia_physicsnemo-1.3.0.dist-info/entry_points.txt
nvidia_physicsnemo-1.3.0.dist-info/top_level.txt
nvidia_physicsnemo-1.3.0.dist-info/RECORD
